{
	"manifest_version": 2,
	"requires": {
		"MediaWiki": ">= 1.31.0"
	},
	"name": "KNAuth",
	"version": "0.1",
	"author": "Ayke van Laethem",
	"url": "https://github.com/aykevl/knauth",
	"description": "Authenticate users against Karpe Noktem's member database.",
	"license-name": "Public domain",
	"Hooks": {
		"UserLoadFromSession": "efKNAuthFromSession",
		"PersonalUrls": "efKNAuthPersonalUrls",
		"LinkEnd": "KarpeNoktem\\KNAuth\\Auth::efKNAuthLinkEnd"
	},
	"AutoloadNamespaces": {
		"KarpeNoktem\\KNAuth\\": "includes/"
	}
}
